{
  "generator-jhipster": {
    "applicationType": "monolith",
    "authenticationType": "jwt",
    "baseName": "CfcNeedManager",
    "blueprints": [],
    "buildTool": "maven",
    "cacheProvider": "ehcache",
    "clientFramework": "angular",
    "clientPackageManager": "npm",
    "creationTimestamp": 1705631498895,
    "databaseType": "sql",
    "devDatabaseType": "h2Disk",
    "devServerPort": 4200,
    "enableHibernateCache": true,
    "enableSwaggerCodegen": false,
    "enableTranslation": true,
    "entities": [],
    "gitCompany": "",
    "jhiPrefix": "jhi",
    "jhipsterVersion": "8.1.0",
    "jwtSecretKey": "OGM2ZjM4YTliOTEyODkwMWE0NTg4MmMzY2I4NDM2NTJkODhlYTczMzM3M2ZiMzYwNDZlMDdkYjI5NDZkODQ0ODJjY2I2ZWM3MmEzNmQ2OWUxM2FhMDEyZTFlYTQ5OTBmOWNlMmExNjdkYmQwYmQ1OTQ4Mzk1ZGNhN2JlYzk5NjI=",
    "languages": ["fr", "en"],
    "messageBroker": false,
    "nativeLanguage": "fr",
    "packageFolder": "cm/cfc/need",
    "packageName": "cm.cfc.need",
    "prodDatabaseType": "postgresql",
    "searchEngine": false,
    "serverPort": 8080,
    "serviceDiscoveryType": false,
    "testFrameworks": ["cypress"],
    "useSass": true,
    "websocket": false,
    "withAdminUi": true
  },
  "git-company": "fouetieu",
  "git-provider": "GitHub",
  "repository-name": "cfc-need-manager"
}
